boppf/__init__.py
boppf/boppf.py
boppf/utils/__init__.py
boppf/utils/ax.py
boppf/utils/data.py
boppf/utils/particle_packing.py
boppf/utils/plotting.py
boppf/utils/run_executable.py
boppf-0.1.0.dist-info/LICENSE
boppf-0.1.0.dist-info/WHEEL
boppf-0.1.0.dist-info/METADATA
boppf-0.1.0.dist-info/RECORD
