Metadata-Version: 2.1
Name: boppf
Version: 0.1.0
Summary: Bayesian optimization of particle packing fractions.
Author-email: "Sterling G. Baird" <sterling.baird@utah.edu>
Requires-Python: >=3.7,<3.10
Classifier: License :: OSI Approved :: MIT License
Classifier: Programming Language :: Python :: 3.7
Classifier: Programming Language :: Python :: 3.8
Classifier: Programming Language :: Python :: 3.9
Classifier: Operating System :: OS Independent
Requires-Dist: ax-platform
Requires-Dist: pyro-ppl
Requires-Dist: ray[tune]
Requires-Dist: tqdm
Requires-Dist: psutil
Requires-Dist: kaleido
Project-URL: Home, https://github.com/sparks-baird/boppf
